excel2dict/__init__.py
excel2dict/converter.py
excel2dict/helper.py
excel2dict/serial_value_handler.py
excel2dict/sheets_definition.py
excel2dict-0.0.2.dist-info/LICENSE
excel2dict-0.0.2.dist-info/METADATA
excel2dict-0.0.2.dist-info/WHEEL
excel2dict-0.0.2.dist-info/entry_points.txt
excel2dict-0.0.2.dist-info/top_level.txt
excel2dict-0.0.2.dist-info/RECORD
