Metadata-Version: 2.1
Name: excel2dict
Version: 0.0.2
Summary: A converting excel file to python data structure package
Home-page: https://github.com/rwakaba/excel2dict
Author: Ryosuke Wakaba
Author-email: wakaba.ryosule@gmail.com
License: UNKNOWN
Platform: UNKNOWN
Classifier: Programming Language :: Python :: 3
Classifier: License :: OSI Approved :: MIT License
Classifier: Operating System :: OS Independent
Requires-Dist: PyYAML
Requires-Dist: xlrd
